[{"line":1,"elements":[{"start_timestamp":"2022-11-09T19:55:12.195Z","line":27,"name":"caso de pruebas name vacio","description":"","id":"caso-de-pruebas-name-vacio","type":"scenario","keyword":"Scenario Outline","steps":[{"name":"url 'https:\/\/reqres.in\/api\/users'","result":{"duration":3354800,"status":"passed"},"match":{"location":"karate","arguments":[]},"keyword":"Given","line":21},{"name":"request {\"name\": , \"job\": \"QAs\"}","result":{"duration":73836600,"status":"passed"},"match":{"location":"karate","arguments":[]},"keyword":"When","line":22},{"name":"method POST","result":{"duration":2196683200,"status":"passed"},"match":{"location":"karate","arguments":[]},"keyword":"And","line":23,"doc_string":{"content_type":"","value":"14:55:13.557 request:\n1 > POST https:\/\/reqres.in\/api\/users\n1 > Content-Type: application\/json; charset=UTF-8\n1 > Content-Length: 23\n1 > Host: reqres.in\n1 > Connection: Keep-Alive\n1 > User-Agent: Apache-HttpClient\/4.5.13 (Java\/1.8.0_321)\n1 > Accept-Encoding: gzip,deflate\n{\"name\":\"\",\"job\":\"QAs\"}\n\n14:55:14.480 response time in milliseconds: 915\n1 < 201\n1 < Date: Wed, 09 Nov 2022 19:55:15 GMT\n1 < Content-Type: application\/json; charset=utf-8\n1 < Content-Length: 73\n1 < Connection: keep-alive\n1 < X-Powered-By: Express\n1 < Access-Control-Allow-Origin: *\n1 < Etag: W\/\"49-GMphJLBjg14sqPfSWoUXRgDbR\/k\"\n1 < Via: 1.1 vegur\n1 < CF-Cache-Status: DYNAMIC\n1 < Report-To: {\"endpoints\":[{\"url\":\"https:\\\/\\\/a.nel.cloudflare.com\\\/report\\\/v3?s=XllIMmohZYDYY85rWiZvl2dynqQfRMpFcW57zGwfXBjKT14Z%2Bmka28cFYsH11A5QhJdQApzL9a24HykU1Y0NkVEihfdqibJhKIaQpLts0nCwMOWhUmgPJtLrYg%3D%3D\"}],\"group\":\"cf-nel\",\"max_age\":604800}\n1 < NEL: {\"success_fraction\":0,\"report_to\":\"cf-nel\",\"max_age\":604800}\n1 < Server: cloudflare\n1 < CF-RAY: 76791adb8f7b8dfc-MIA\n{\"name\":\"\",\"job\":\"QAs\",\"id\":\"969\",\"createdAt\":\"2022-11-09T19:55:15.331Z\"}\n\n","line":23}},{"name":"status 201","result":{"duration":32500,"status":"passed"},"match":{"location":"karate","arguments":[]},"keyword":"Then","line":24}],"tags":[{"name":"@casoPost","line":19}]},{"start_timestamp":"2022-11-09T19:55:12.195Z","line":28,"name":"caso de pruebas name nulo","description":"","id":"caso-de-pruebas-name-nulo","type":"scenario","keyword":"Scenario Outline","steps":[{"name":"url 'https:\/\/reqres.in\/api\/users'","result":{"duration":3354700,"status":"passed"},"match":{"location":"karate","arguments":[]},"keyword":"Given","line":21},{"name":"request {\"name\": null, \"job\": \"QAs\"}","result":{"duration":73836800,"status":"passed"},"match":{"location":"karate","arguments":[]},"keyword":"When","line":22},{"name":"method POST","result":{"duration":2196385800,"status":"passed"},"match":{"location":"karate","arguments":[]},"keyword":"And","line":23,"doc_string":{"content_type":"","value":"14:55:13.557 request:\n1 > POST https:\/\/reqres.in\/api\/users\n1 > Content-Type: application\/json; charset=UTF-8\n1 > Content-Length: 25\n1 > Host: reqres.in\n1 > Connection: Keep-Alive\n1 > User-Agent: Apache-HttpClient\/4.5.13 (Java\/1.8.0_321)\n1 > Accept-Encoding: gzip,deflate\n{\"name\":null,\"job\":\"QAs\"}\n\n14:55:14.480 response time in milliseconds: 915\n1 < 201\n1 < Date: Wed, 09 Nov 2022 19:55:15 GMT\n1 < Content-Type: application\/json; charset=utf-8\n1 < Content-Length: 75\n1 < Connection: keep-alive\n1 < X-Powered-By: Express\n1 < Access-Control-Allow-Origin: *\n1 < Etag: W\/\"4b-Cn43yFjnCC6wLWzDn1lBaHRlAH0\"\n1 < Via: 1.1 vegur\n1 < CF-Cache-Status: DYNAMIC\n1 < Report-To: {\"endpoints\":[{\"url\":\"https:\\\/\\\/a.nel.cloudflare.com\\\/report\\\/v3?s=yeSbHVLm3xh6l3%2FJvhoo0X7mEExS0a6Ho22c1XAOyqmtLiaZLQrl8HJSk5J9F%2FfhLf%2BEeeZH7Fkm7cqFz2CrYJARCIueu%2Bkot9v7ePsSqlDOc4eNevks31F41A%3D%3D\"}],\"group\":\"cf-nel\",\"max_age\":604800}\n1 < NEL: {\"success_fraction\":0,\"report_to\":\"cf-nel\",\"max_age\":604800}\n1 < Server: cloudflare\n1 < CF-RAY: 76791adb897d67b4-MIA\n{\"name\":null,\"job\":\"QAs\",\"id\":\"790\",\"createdAt\":\"2022-11-09T19:55:15.327Z\"}\n\n","line":23}},{"name":"status 201","result":{"duration":62500,"status":"passed"},"match":{"location":"karate","arguments":[]},"keyword":"Then","line":24}],"tags":[{"name":"@casoPost","line":19}]},{"start_timestamp":"2022-11-09T19:55:12.195Z","line":29,"name":"caso de pruebas name 3 letras","description":"","id":"caso-de-pruebas-name-3-letras","type":"scenario","keyword":"Scenario Outline","steps":[{"name":"url 'https:\/\/reqres.in\/api\/users'","result":{"duration":3354600,"status":"passed"},"match":{"location":"karate","arguments":[]},"keyword":"Given","line":21},{"name":"request {\"name\": \"Jei\", \"job\": \"QAs\"}","result":{"duration":73672900,"status":"passed"},"match":{"location":"karate","arguments":[]},"keyword":"When","line":22},{"name":"method POST","result":{"duration":2198852900,"status":"passed"},"match":{"location":"karate","arguments":[]},"keyword":"And","line":23,"doc_string":{"content_type":"","value":"14:55:13.557 request:\n1 > POST https:\/\/reqres.in\/api\/users\n1 > Content-Type: application\/json; charset=UTF-8\n1 > Content-Length: 26\n1 > Host: reqres.in\n1 > Connection: Keep-Alive\n1 > User-Agent: Apache-HttpClient\/4.5.13 (Java\/1.8.0_321)\n1 > Accept-Encoding: gzip,deflate\n{\"name\":\"Jei\",\"job\":\"QAs\"}\n\n14:55:14.479 response time in milliseconds: 915\n1 < 201\n1 < Date: Wed, 09 Nov 2022 19:55:15 GMT\n1 < Content-Type: application\/json; charset=utf-8\n1 < Content-Length: 76\n1 < Connection: keep-alive\n1 < X-Powered-By: Express\n1 < Access-Control-Allow-Origin: *\n1 < Etag: W\/\"4c-9tXhb2Y\/jtNtGkm93saLWlJuSUk\"\n1 < Via: 1.1 vegur\n1 < CF-Cache-Status: DYNAMIC\n1 < Report-To: {\"endpoints\":[{\"url\":\"https:\\\/\\\/a.nel.cloudflare.com\\\/report\\\/v3?s=A5fRNwXLkRpOEAWbDLA1Z1QF4gQnbM7GwFQfCyGDYb3v3HLB81xdluYRJeK66bmqA%2F7u7kLsyqL8qNez791Eyd2KcP3MSOena0%2F4F4gkbNMfbwuNixpqwd8pbA%3D%3D\"}],\"group\":\"cf-nel\",\"max_age\":604800}\n1 < NEL: {\"success_fraction\":0,\"report_to\":\"cf-nel\",\"max_age\":604800}\n1 < Server: cloudflare\n1 < CF-RAY: 76791adb8a952293-MIA\n{\"name\":\"Jei\",\"job\":\"QAs\",\"id\":\"791\",\"createdAt\":\"2022-11-09T19:55:15.318Z\"}\n\n","line":23}},{"name":"status 201","result":{"duration":22800,"status":"passed"},"match":{"location":"karate","arguments":[]},"keyword":"Then","line":24}],"tags":[{"name":"@casoPost","line":19}]},{"start_timestamp":"2022-11-09T19:55:12.195Z","line":30,"name":"caso de pruebas sin campo name","description":"","id":"caso-de-pruebas-sin-campo-name","type":"scenario","keyword":"Scenario Outline","steps":[{"name":"url 'https:\/\/reqres.in\/api\/users'","result":{"duration":3354700,"status":"passed"},"match":{"location":"karate","arguments":[]},"keyword":"Given","line":21},{"name":"request {\"\": , \"job\": \"QAs\"}","result":{"duration":73808800,"status":"passed"},"match":{"location":"karate","arguments":[]},"keyword":"When","line":22},{"name":"method POST","result":{"duration":2198297900,"status":"passed"},"match":{"location":"karate","arguments":[]},"keyword":"And","line":23,"doc_string":{"content_type":"","value":"14:55:13.557 request:\n1 > POST https:\/\/reqres.in\/api\/users\n1 > Content-Type: application\/json; charset=UTF-8\n1 > Content-Length: 19\n1 > Host: reqres.in\n1 > Connection: Keep-Alive\n1 > User-Agent: Apache-HttpClient\/4.5.13 (Java\/1.8.0_321)\n1 > Accept-Encoding: gzip,deflate\n{\"\":\"\",\"job\":\"QAs\"}\n\n14:55:14.480 response time in milliseconds: 914\n1 < 201\n1 < Date: Wed, 09 Nov 2022 19:55:15 GMT\n1 < Content-Type: application\/json; charset=utf-8\n1 < Content-Length: 69\n1 < Connection: keep-alive\n1 < X-Powered-By: Express\n1 < Access-Control-Allow-Origin: *\n1 < Etag: W\/\"45-OuRAXUuCH+8pm4aF4hOxTadmnu4\"\n1 < Via: 1.1 vegur\n1 < CF-Cache-Status: DYNAMIC\n1 < Report-To: {\"endpoints\":[{\"url\":\"https:\\\/\\\/a.nel.cloudflare.com\\\/report\\\/v3?s=Bgx9wofXfDMtgHrhzR4OP4cL5wI64m9lV%2Bv0rxw33Q1MxYGBLu8J4awv2IjfJ0XNSx9GHdLQhSzQ3YRclOOpkmwuHFcbyhoy7Htu0HYKJr%2Fz8Zh2kJzCeGxX5w%3D%3D\"}],\"group\":\"cf-nel\",\"max_age\":604800}\n1 < NEL: {\"success_fraction\":0,\"report_to\":\"cf-nel\",\"max_age\":604800}\n1 < Server: cloudflare\n1 < CF-RAY: 76791adb8b5e8dcd-MIA\n{\"\":\"\",\"job\":\"QAs\",\"id\":\"675\",\"createdAt\":\"2022-11-09T19:55:15.327Z\"}\n\n","line":23}},{"name":"status 201","result":{"duration":25000,"status":"passed"},"match":{"location":"karate","arguments":[]},"keyword":"Then","line":24}],"tags":[{"name":"@casoPost","line":19}]},{"start_timestamp":"2022-11-09T19:55:14.531Z","line":31,"name":"caso de pruebas job vacio","description":"","id":"caso-de-pruebas-job-vacio","type":"scenario","keyword":"Scenario Outline","steps":[{"name":"url 'https:\/\/reqres.in\/api\/users'","result":{"duration":3978700,"status":"passed"},"match":{"location":"karate","arguments":[]},"keyword":"Given","line":21},{"name":"request {\"name\": \"Jason\", \"job\": \"\"}","result":{"duration":541900,"status":"passed"},"match":{"location":"karate","arguments":[]},"keyword":"When","line":22},{"name":"method POST","result":{"duration":492893700,"status":"passed"},"match":{"location":"karate","arguments":[]},"keyword":"And","line":23,"doc_string":{"content_type":"","value":"14:55:14.546 request:\n1 > POST https:\/\/reqres.in\/api\/users\n1 > Content-Type: application\/json; charset=UTF-8\n1 > Content-Length: 25\n1 > Host: reqres.in\n1 > Connection: Keep-Alive\n1 > User-Agent: Apache-HttpClient\/4.5.13 (Java\/1.8.0_321)\n1 > Accept-Encoding: gzip,deflate\n{\"name\":\"Jason\",\"job\":\"\"}\n\n14:55:15.029 response time in milliseconds: 482\n1 < 201\n1 < Date: Wed, 09 Nov 2022 19:55:15 GMT\n1 < Content-Type: application\/json; charset=utf-8\n1 < Content-Length: 75\n1 < Connection: keep-alive\n1 < X-Powered-By: Express\n1 < Access-Control-Allow-Origin: *\n1 < Etag: W\/\"4b-LrQetlFwH2kyBQ4XVpfOAcLYhHQ\"\n1 < Via: 1.1 vegur\n1 < CF-Cache-Status: DYNAMIC\n1 < Report-To: {\"endpoints\":[{\"url\":\"https:\\\/\\\/a.nel.cloudflare.com\\\/report\\\/v3?s=BqJsuzxIGNP95t8nXAfHp2E7r%2F43BJaxgoACW6VcygT6spY6w1z8y7QSxU1CMtPwsjLtWJrMBWWibE2GxDllEFMVDTwotGa1EWEpyaB6jbeUGi0lVI%2BvwvcTZA%3D%3D\"}],\"group\":\"cf-nel\",\"max_age\":604800}\n1 < NEL: {\"success_fraction\":0,\"report_to\":\"cf-nel\",\"max_age\":604800}\n1 < Server: cloudflare\n1 < CF-RAY: 76791adef8e8b3cd-MIA\n{\"name\":\"Jason\",\"job\":\"\",\"id\":\"955\",\"createdAt\":\"2022-11-09T19:55:15.916Z\"}\n\n","line":23}},{"name":"status 201","result":{"duration":28100,"status":"passed"},"match":{"location":"karate","arguments":[]},"keyword":"Then","line":24}],"tags":[{"name":"@casoPost","line":19}]},{"start_timestamp":"2022-11-09T19:55:14.546Z","line":32,"name":"caso de pruebas job nulo","description":"","id":"caso-de-pruebas-job-nulo","type":"scenario","keyword":"Scenario Outline","steps":[{"name":"url 'https:\/\/reqres.in\/api\/users'","result":{"duration":1649400,"status":"passed"},"match":{"location":"karate","arguments":[]},"keyword":"Given","line":21},{"name":"request {\"name\": \"Jason\", \"job\": null}","result":{"duration":539000,"status":"passed"},"match":{"location":"karate","arguments":[]},"keyword":"When","line":22},{"name":"method POST","result":{"duration":511560600,"status":"passed"},"match":{"location":"karate","arguments":[]},"keyword":"And","line":23,"doc_string":{"content_type":"","value":"14:55:14.563 request:\n1 > POST https:\/\/reqres.in\/api\/users\n1 > Content-Type: application\/json; charset=UTF-8\n1 > Content-Length: 27\n1 > Host: reqres.in\n1 > Connection: Keep-Alive\n1 > User-Agent: Apache-HttpClient\/4.5.13 (Java\/1.8.0_321)\n1 > Accept-Encoding: gzip,deflate\n{\"name\":\"Jason\",\"job\":null}\n\n14:55:15.066 response time in milliseconds: 502\n1 < 201\n1 < Date: Wed, 09 Nov 2022 19:55:16 GMT\n1 < Content-Type: application\/json; charset=utf-8\n1 < Content-Length: 77\n1 < Connection: keep-alive\n1 < X-Powered-By: Express\n1 < Access-Control-Allow-Origin: *\n1 < Etag: W\/\"4d-GZm0KyjDjjKCU6GfUenmWhwk2uU\"\n1 < Via: 1.1 vegur\n1 < CF-Cache-Status: DYNAMIC\n1 < Report-To: {\"endpoints\":[{\"url\":\"https:\\\/\\\/a.nel.cloudflare.com\\\/report\\\/v3?s=1topdlyq7ZeOQLOTo9AGMPmLdwYfwFI74W9Poi8PDUMYMvOtnAFaO2Hz5ZUvew1AEVf04%2Fi7RXZcPtf8b%2BgE2bypa9HOeF23YrfqVOTM%2FH6lVXAcxoVeFpIPmw%3D%3D\"}],\"group\":\"cf-nel\",\"max_age\":604800}\n1 < NEL: {\"success_fraction\":0,\"report_to\":\"cf-nel\",\"max_age\":604800}\n1 < Server: cloudflare\n1 < CF-RAY: 76791adf7d5f3712-MIA\n{\"name\":\"Jason\",\"job\":null,\"id\":\"110\",\"createdAt\":\"2022-11-09T19:55:15.955Z\"}\n\n","line":23}},{"name":"status 201","result":{"duration":31100,"status":"passed"},"match":{"location":"karate","arguments":[]},"keyword":"Then","line":24}],"tags":[{"name":"@casoPost","line":19}]},{"start_timestamp":"2022-11-09T19:55:14.546Z","line":33,"name":"caso de pruebas job 3 letras","description":"","id":"caso-de-pruebas-job-3-letras","type":"scenario","keyword":"Scenario Outline","steps":[{"name":"url 'https:\/\/reqres.in\/api\/users'","result":{"duration":1949100,"status":"passed"},"match":{"location":"karate","arguments":[]},"keyword":"Given","line":21},{"name":"request {\"name\": \"Jason\", \"job\": \"QAAutomation\"}","result":{"duration":557800,"status":"passed"},"match":{"location":"karate","arguments":[]},"keyword":"When","line":22},{"name":"method POST","result":{"duration":456553700,"status":"passed"},"match":{"location":"karate","arguments":[]},"keyword":"And","line":23,"doc_string":{"content_type":"","value":"14:55:14.560 request:\n1 > POST https:\/\/reqres.in\/api\/users\n1 > Content-Type: application\/json; charset=UTF-8\n1 > Content-Length: 37\n1 > Host: reqres.in\n1 > Connection: Keep-Alive\n1 > User-Agent: Apache-HttpClient\/4.5.13 (Java\/1.8.0_321)\n1 > Accept-Encoding: gzip,deflate\n{\"name\":\"Jason\",\"job\":\"QAAutomation\"}\n\n14:55:15.009 response time in milliseconds: 446\n1 < 201\n1 < Date: Wed, 09 Nov 2022 19:55:15 GMT\n1 < Content-Type: application\/json; charset=utf-8\n1 < Content-Length: 87\n1 < Connection: keep-alive\n1 < X-Powered-By: Express\n1 < Access-Control-Allow-Origin: *\n1 < Etag: W\/\"57-YeZ+5NOy\/7tZlf+vi0NpIiqxftc\"\n1 < Via: 1.1 vegur\n1 < CF-Cache-Status: DYNAMIC\n1 < Report-To: {\"endpoints\":[{\"url\":\"https:\\\/\\\/a.nel.cloudflare.com\\\/report\\\/v3?s=MzcwuTX0zfyCwCo98JNNjbL5UnROna2BJwH%2BZodPuzaLKTjtWOcdd90ZuhTgb2%2BuRg6t%2BDrrjeIJxSxw611%2F98hSM%2FnEqb5%2B9xEnMKsn%2FSFVzZmY%2BOQxv4Sz1g%3D%3D\"}],\"group\":\"cf-nel\",\"max_age\":604800}\n1 < NEL: {\"success_fraction\":0,\"report_to\":\"cf-nel\",\"max_age\":604800}\n1 < Server: cloudflare\n1 < CF-RAY: 76791adf0e6db3b6-MIA\n{\"name\":\"Jason\",\"job\":\"QAAutomation\",\"id\":\"290\",\"createdAt\":\"2022-11-09T19:55:15.882Z\"}\n\n","line":23}},{"name":"status 201","result":{"duration":29400,"status":"passed"},"match":{"location":"karate","arguments":[]},"keyword":"Then","line":24}],"tags":[{"name":"@casoPost","line":19}]},{"start_timestamp":"2022-11-09T19:55:14.531Z","line":34,"name":"caso de pruebas sin campo job","description":"","id":"caso-de-pruebas-sin-campo-job","type":"scenario","keyword":"Scenario Outline","steps":[{"name":"url 'https:\/\/reqres.in\/api\/users'","result":{"duration":3823600,"status":"passed"},"match":{"location":"karate","arguments":[]},"keyword":"Given","line":21},{"name":"request {\"name\": \"Jason\", \"\": \"\"}","result":{"duration":902600,"status":"passed"},"match":{"location":"karate","arguments":[]},"keyword":"When","line":22},{"name":"method POST","result":{"duration":518524100,"status":"passed"},"match":{"location":"karate","arguments":[]},"keyword":"And","line":23,"doc_string":{"content_type":"","value":"14:55:14.545 request:\n1 > POST https:\/\/reqres.in\/api\/users\n1 > Content-Type: application\/json; charset=UTF-8\n1 > Content-Length: 22\n1 > Host: reqres.in\n1 > Connection: Keep-Alive\n1 > User-Agent: Apache-HttpClient\/4.5.13 (Java\/1.8.0_321)\n1 > Accept-Encoding: gzip,deflate\n{\"name\":\"Jason\",\"\":\"\"}\n\n14:55:15.054 response time in milliseconds: 507\n1 < 201\n1 < Date: Wed, 09 Nov 2022 19:55:16 GMT\n1 < Content-Type: application\/json; charset=utf-8\n1 < Content-Length: 72\n1 < Connection: keep-alive\n1 < X-Powered-By: Express\n1 < Access-Control-Allow-Origin: *\n1 < Etag: W\/\"48-UqALWpmuqxmSYB6tLaBuRSzf7uY\"\n1 < Via: 1.1 vegur\n1 < CF-Cache-Status: DYNAMIC\n1 < Report-To: {\"endpoints\":[{\"url\":\"https:\\\/\\\/a.nel.cloudflare.com\\\/report\\\/v3?s=0Hvf%2FangZzha7jsnEY0t5Qif2H1%2B93tU5Ommec0lJuhOW8%2BsqSqWk1ykvmRL4y7Qzwl%2FZBW%2B8ysb7ub8jPBDDROzKodl8GZ%2F0XekojjYy3YHInaUdQdTHLppPw%3D%3D\"}],\"group\":\"cf-nel\",\"max_age\":604800}\n1 < NEL: {\"success_fraction\":0,\"report_to\":\"cf-nel\",\"max_age\":604800}\n1 < Server: cloudflare\n1 < CF-RAY: 76791adf79f9036a-MIA\n{\"name\":\"Jason\",\"\":\"\",\"id\":\"111\",\"createdAt\":\"2022-11-09T19:55:15.946Z\"}\n\n","line":23}},{"name":"status 201","result":{"duration":23100,"status":"passed"},"match":{"location":"karate","arguments":[]},"keyword":"Then","line":24}],"tags":[{"name":"@casoPost","line":19}]}],"name":"REST\/KarateTest.feature","description":"plan de pruebas api REST","id":"plan-de-pruebas-api-rest","keyword":"Feature","uri":"REST\/KarateTest.feature"}]